async_throttle/__init__.py
async_throttle/test_throttle.py
async_throttle/test_token_bucket.py
async_throttle/throttle.py
async_throttle/token_bucket.py
async_throttle-1.0.0.dist-info/METADATA
async_throttle-1.0.0.dist-info/WHEEL
async_throttle-1.0.0.dist-info/RECORD
