Metadata-Version: 2.1
Name: async-throttle
Version: 1.0.0
Summary: Multipurpose asyncio throttle
License: MIT
Author: Joe Nudell
Author-email: jnudell@hks.harvard.edu
Requires-Python: >=3.10,<4.0
Classifier: License :: OSI Approved :: MIT License
Classifier: Programming Language :: Python :: 3
Classifier: Programming Language :: Python :: 3.10
Classifier: Programming Language :: Python :: 3.11
